bstadlbauer/p300speller/__init__.py
bstadlbauer/p300speller/conf_files/default.cfg
bstadlbauer/p300speller/flash_images/einstein.jpg
bstadlbauer/p300speller/number_images/1.jpg
bstadlbauer/p300speller/number_images/2.jpg
bstadlbauer/p300speller/number_images/3.jpg
bstadlbauer/p300speller/number_images/4.jpg
bstadlbauer/p300speller/number_images/5.jpg
bstadlbauer/p300speller/number_images/6.jpg
bstadlbauer/p300speller/number_images/7.jpg
bstadlbauer/p300speller/number_images/8.jpg
bstadlbauer/p300speller/number_images/9.jpg
bstadlbauer/p300speller/number_images/Number.xcf
bstadlbauer/p300speller/p300_speller.py
bstadlbauer.p300speller-0.1.1.dist-info/entry_points.txt
bstadlbauer.p300speller-0.1.1.dist-info/LICENSE
bstadlbauer.p300speller-0.1.1.dist-info/WHEEL
bstadlbauer.p300speller-0.1.1.dist-info/METADATA
bstadlbauer.p300speller-0.1.1.dist-info/RECORD
