Metadata-Version: 2.1
Name: bstadlbauer.p300speller
Version: 0.1.1
Summary: P300 speller based on LSL
Home-page: https://github.com/bstadlbauer/lsl-p300-speller
License: GPL-3.0-only
Author: Bernhard Stadlbauer
Author-email: b.stadlbauer@gmx.net
Requires-Python: >=3.6.1,<4.0.0
Classifier: License :: OSI Approved :: GNU General Public License v3 (GPLv3)
Classifier: Programming Language :: Python :: 3
Classifier: Programming Language :: Python :: 3.7
Classifier: Programming Language :: Python :: 3.8
Classifier: Programming Language :: Python :: 3.9
Requires-Dist: Pillow (>=8.0.1,<9.0.0)
Requires-Dist: numpy (>=1.19.2,<2.0.0)
Requires-Dist: pylsl (>=1.13.6,<2.0.0)
Project-URL: Repository, https://github.com/bstadlbauer/lsl-p300-speller
